{
  "title": "Iv Ceban huiduit",
  "content": "Stimați concetățeni,\n\nTot a circulat pe internetul mioritic filmări de la cum a fost huiduit domnul primar de Chișinău la concertul zdubilor de la arena. Aparent (re-)sentimentul e destul de puternic. La fel, aparent, IV Ceban nu a urcat pe scena la noapte de anul nou, așa cum era așteptat. Probabil o avut frica de o situație similară (sper).\n\nMă gândesc că mai ales anul asta, am demonstrat că putem lupta pentru valorile in care credem că ne va face țara mai buna. În același timp, m-am săturat să fiu reprezentat la nivel de oraș (sau orice instituție publică de un demagog care crede că prostește pe cineva cu schimbul macazului din 'sațalist' in pro-european. Mai adaugi și faptul că tulbura democrația și joaca în interese străine de banii noștri publici și bugetul neaprobat (pt mine aici dispare orice comparație cu Chirtoacă - schimbările cosmetice din oraș putea să le facă oricine cu un grad mediu de competență). \n\nȘi iată aici apare întrebarea: luând chestiile astea in considerare, de ce sa nu organizam un prostest autentic? Am demonstrat în trecut că putem sa ne strângem pentru o idee în care credem. Și mai și reabilităm conceptul de protest, după ce l-o spălăcit șoriștii cu grecika și tușonca.\n\nAșa, semi-indemn, semi-food for thought. Dar eu cred că ne putem face auziți, in contextul resentimentelor colective. De altfel prin lipsa de acțiune încurajam așa indivizi în poziție de putere în continuare. \n\nMulțumesc!",
  "metadata": {
    "id": 29,
    "source_url": "https://reddit.com/r/moldova/comments/1q21suc/iv_ceban_huiduit/"
  }
}